LICENSE
README.md
pyproject.toml
setup.cfg
setup.py
SBbadger/__init__.py
SBbadger/_version.py
SBbadger/buildNetworks.py
SBbadger/generate.py
SBbadger/generate_serial.py
SBbadger/mass_action.py
SBbadger.egg-info/PKG-INFO
SBbadger.egg-info/SOURCES.txt
SBbadger.egg-info/dependency_links.txt
SBbadger.egg-info/requires.txt
SBbadger.egg-info/top_level.txt