Metadata-Version: 2.1
Name: SBbadger
Version: 1.4.5
Summary: Synthetic biochemical reaction networks with definable degree distributions.
Home-page: https://github.com/sys-bio/SBbadger
Download-URL: https://github.com/sys-bio/SBbadger/archive/refs/tags/v1.4.5.tar.gz
Author: Michael Kochen
Author-email: kochenma@uw.edu
License: Apache
Keywords: Systems biology,Benchmark Models
Classifier: Development Status :: 5 - Production/Stable
Classifier: Intended Audience :: Developers
Classifier: Topic :: Software Development :: Build Tools
Classifier: License :: OSI Approved :: Apache Software License
Classifier: Programming Language :: Python :: 3.7
Classifier: Programming Language :: Python :: 3.8
Classifier: Programming Language :: Python :: 3.9
License-File: LICENSE
